mmwave/__init__.py
mmwave/clustering/__init__.py
mmwave/clustering/clustering.py
mmwave/dataloader/__init__.py
mmwave/dataloader/adc.py
mmwave/dataloader/file_parse.py
mmwave/dataloader/radars.py
mmwave/dataloader/utils.py
mmwave/dsp/ZoomFFT.py
mmwave/dsp/__init__.py
mmwave/dsp/angle_estimation.py
mmwave/dsp/cfar.py
mmwave/dsp/compensation.py
mmwave/dsp/doppler_processing.py
mmwave/dsp/noise_removal.py
mmwave/dsp/range_processing.py
mmwave/dsp/utils.py
mmwave/tests/__init__.py
mmwave/tracking/__init__.py
mmwave/tracking/ekf.py
mmwave/tracking/ekf_utils.py
mmwave/tracking/gtrack_module.py
mmwave/tracking/gtrack_test.py
mmwave/tracking/gtrack_unit.py
mmwave/tracking/gtrack_visualize.py
openradar-1.0.1.dist-info/LICENSE
openradar-1.0.1.dist-info/METADATA
openradar-1.0.1.dist-info/WHEEL
openradar-1.0.1.dist-info/top_level.txt
openradar-1.0.1.dist-info/RECORD
