Metadata-Version: 2.1
Name: openradar
Version: 1.0.1
Summary: A mmWave radar data processing library
Home-page: UNKNOWN
Author: Edwin Pan, Jingning Tang, Dashiell Kosaka, Arjun Gupta, Ruihao Yao
Author-email: presenseradar@gmail.com
License: UNKNOWN
Platform: UNKNOWN
Classifier: Programming Language :: Python :: 3
Classifier: License :: OSI Approved :: MIT License
Classifier: Operating System :: OS Independent
